pychastic/__init__.py
pychastic/sde_problem.py
pychastic/sde_solver.py
pychastic/vectorized_I_generation.py
pychastic/wiener_integral_moments.py
pychastic-0.2.2.dist-info/LICENSE
pychastic-0.2.2.dist-info/METADATA
pychastic-0.2.2.dist-info/WHEEL
pychastic-0.2.2.dist-info/top_level.txt
pychastic-0.2.2.dist-info/RECORD
