Metadata-Version: 2.1
Name: pychastic
Version: 0.2.2
Summary: Solvers for stochastic differential equations
Home-page: https://github.com/RadostW/stochastic
Author: Radost Waszkiewicz & Maciej Bartczak
Author-email: radost.waszkiewicz@gmail.com
License: MIT
Project-URL: Documentation, https://pychastic.readthedocs.io
Project-URL: Source, https://github.com/RadostW/stochastic
Platform: UNKNOWN
License-File: LICENSE
Requires-Dist: jax
Requires-Dist: jaxlib
Requires-Dist: numpy
Requires-Dist: sortedcontainers
Requires-Dist: tqdm
